gotranx/__init__.py
gotranx/__main__.py
gotranx/_enum.py
gotranx/atoms.py
gotranx/exceptions.py
gotranx/expressions.py
gotranx/load.py
gotranx/myokit.py
gotranx/ode.lark
gotranx/ode.py
gotranx/ode_component.py
gotranx/parser.py
gotranx/save.py
gotranx/schemes.py
gotranx/sympytools.py
gotranx/transformer.py
gotranx/units.py
gotranx/cli/__init__.py
gotranx/cli/cellml2ode.py
gotranx/cli/gotran2c.py
gotranx/cli/gotran2julia.py
gotranx/cli/gotran2py.py
gotranx/cli/utils.py
gotranx/codegen/__init__.py
gotranx/codegen/base.py
gotranx/codegen/c.py
gotranx/codegen/jax.py
gotranx/codegen/julia.py
gotranx/codegen/ode.py
gotranx/codegen/python.py
gotranx/templates/__init__.py
gotranx/templates/c.py
gotranx/templates/jax.py
gotranx/templates/julia.py
gotranx/templates/python.py
gotranx-1.3.6.dist-info/licenses/LICENSE
gotranx-1.3.6.dist-info/METADATA
gotranx-1.3.6.dist-info/WHEEL
gotranx-1.3.6.dist-info/entry_points.txt
gotranx-1.3.6.dist-info/top_level.txt
gotranx-1.3.6.dist-info/RECORD
