Metadata-Version: 2.4
Name: gotranx
Version: 1.3.6
Summary: A declarative language describing ordinary differential equations
Author-email: Henrik Finsberg <henriknf@simula.no>
License: MIT
Project-URL: Homepage, https://github.com/finsberg/gotranx
Keywords: parser,lark,gotran,ode
Classifier: License :: OSI Approved :: MIT License
Classifier: Programming Language :: Python :: 3
Requires-Python: >=3.9
License-File: LICENSE
Requires-Dist: attrs
Requires-Dist: lark
Requires-Dist: pint
Requires-Dist: rich-click
Requires-Dist: structlog
Requires-Dist: sympy
Requires-Dist: typer
Requires-Dist: myokit
Requires-Dist: click<8.2
Requires-Dist: toml; python_version < "3.11"
Requires-Dist: graphlib-backport; python_version < "3.9"
Requires-Dist: typing_extensions; python_version < "3.9"
Provides-Extra: formatters
Requires-Dist: black; extra == "formatters"
Requires-Dist: clang-format-docs; extra == "formatters"
Provides-Extra: dev
Requires-Dist: bump-my-version; extra == "dev"
Requires-Dist: ipython; extra == "dev"
Requires-Dist: pdbpp; extra == "dev"
Requires-Dist: pre-commit; extra == "dev"
Requires-Dist: twine; extra == "dev"
Requires-Dist: wheel; extra == "dev"
Provides-Extra: docs
Requires-Dist: jupyter-book; extra == "docs"
Requires-Dist: jupytext; extra == "docs"
Requires-Dist: scipy; extra == "docs"
Requires-Dist: sphinxcontrib-mermaid; extra == "docs"
Requires-Dist: jax; extra == "docs"
Requires-Dist: numba; extra == "docs"
Requires-Dist: gotranx[formatters]; extra == "docs"
Provides-Extra: test
Requires-Dist: pytest; extra == "test"
Requires-Dist: pytest-cov; extra == "test"
Requires-Dist: jax; extra == "test"
Requires-Dist: cmake; extra == "test"
Requires-Dist: gotranx[formatters]; extra == "test"
Provides-Extra: benchmark
Requires-Dist: pytest-benchmark>=4.0.0; extra == "benchmark"
Requires-Dist: pytest-codspeed~=2.2.0; python_version < "3.13" and extra == "benchmark"
Requires-Dist: gotranx[test]; extra == "benchmark"
Provides-Extra: all
Requires-Dist: gotranx[dev,docs,formatters,test]; extra == "all"
Dynamic: license-file
